[
  {
    "content": "ウルセェ谷口",
    "username": "杉山",
    "id": "1764289627455",
    "createdAt": "2025-11-28T00:27:07.455Z"
  },
  {
    "content": "ちんちん",
    "username": "谷口",
    "id": "1764289596649",
    "createdAt": "2025-11-28T00:26:36.649Z"
  },
  {
    "content": "今日は雨です",
    "username": "神山",
    "id": "1764289081408",
    "createdAt": "2025-11-28T00:18:01.408Z"
  },
  {
    "content": "Testing auth post",
    "username": "testuser",
    "id": "1764288783486",
    "createdAt": "2025-11-28T00:13:03.486Z"
  },
  {
    "content": "こんにちは！",
    "id": "1764288557908",
    "createdAt": "2025-11-28T00:09:17.908Z"
  },
  {
    "content": "Hello from Antigravity",
    "id": "1764288531296",
    "createdAt": "2025-11-28T00:08:51.297Z"
  }
]